{
  "model_name": "mlp-other-rate/trial_48_4e4859",
  "model_type": "MLP",
  "model_format": "torch",
  "model_params": {
    "history_length": 1,
    "hidden_layers": [
      512,
      256,
      128
    ],
    "dropout": 0.3299434925659164,
    "mid_layer_count": 9,
    "mid_layer_size": 181
  },
  "training_params": {
    "max_epochs": 400,
    "batch_size": 339,
    "learning_rate": 0.0017971750656631399,
    "weight_decay": 0.0011632993758806539,
    "checkpoint_interval": 10,
    "seed": 42
  },
  "data_csv": "data/time_aligned_data.csv",
  "timestamp_column": "Date, Time",
  "columns": [
    "TRC-DT",
    "TRC-RT",
    "TRC-PPL1",
    "TRC-PPL2",
    "pH-DT",
    "pH-RT",
    "pH-PPL1",
    "pH-PPL2",
    "cond-DT",
    "cond-PPL1",
    "cond-PPL2",
    "fDOM-RT",
    "fDOM-PPL1",
    "fDOM-PPL2",
    "DO-RT",
    "DO-PPL1",
    "DO-PPL2",
    "TOC-RT",
    "TOC-PPL1",
    "TOC-PPL2",
    "DOC-RT",
    "DOC-PPL1",
    "DOC-PPL2",
    "minutes_since_start"
  ],
  "feature_columns": [
    "TRC-DT",
    "TRC-RT",
    "pH-DT",
    "pH-RT",
    "cond-DT",
    "fDOM-RT",
    "DO-RT",
    "TOC-RT",
    "DOC-RT",
    "minutes_since_start"
  ],
  "target_columns": [
    "TOC-PPL1",
    "TOC-PPL2",
    "DOC-PPL1",
    "DOC-PPL2",
    "pH-PPL1",
    "pH-PPL2"
  ],
  "target_mode": "rate",
  "target_base_columns": [
    "TOC-RT",
    "TOC-RT",
    "DOC-RT",
    "DOC-RT",
    "pH-RT",
    "pH-RT"
  ],
  "split_boundaries": {
    "train_end": 7796,
    "val_end": 9466,
    "test_end": 11138
  },
  "dataset_sizes": {
    "train": 7796,
    "val": 1670,
    "test": 1672
  },
  "input_dim": 10,
  "sequence_length": null,
  "training_history": {
    "epochs": [
      1,
      2,
      3,
      4,
      5,
      6,
      7,
      8,
      9,
      10,
      11,
      12,
      13,
      14,
      15,
      16,
      17,
      18,
      19,
      20,
      21,
      22,
      23,
      24,
      25,
      26,
      27,
      28,
      29,
      30,
      31,
      32,
      33,
      34,
      35,
      36,
      37,
      38,
      39,
      40,
      41,
      42,
      43,
      44,
      45,
      46,
      47,
      48,
      49,
      50,
      51,
      52,
      53,
      54,
      55,
      56,
      57,
      58,
      59,
      60,
      61,
      62,
      63,
      64,
      65,
      66,
      67,
      68,
      69,
      70,
      71,
      72,
      73,
      74,
      75,
      76,
      77,
      78,
      79,
      80,
      81,
      82,
      83,
      84,
      85,
      86,
      87,
      88,
      89,
      90,
      91,
      92,
      93,
      94,
      95,
      96,
      97,
      98,
      99,
      100,
      101,
      102,
      103,
      104,
      105,
      106,
      107,
      108,
      109,
      110,
      111,
      112,
      113,
      114,
      115,
      116,
      117,
      118,
      119,
      120,
      121,
      122,
      123,
      124,
      125,
      126,
      127,
      128,
      129,
      130,
      131,
      132,
      133,
      134,
      135,
      136,
      137,
      138,
      139,
      140,
      141,
      142,
      143,
      144,
      145,
      146,
      147,
      148,
      149,
      150,
      151,
      152,
      153,
      154,
      155,
      156,
      157,
      158,
      159,
      160,
      161,
      162,
      163,
      164,
      165,
      166,
      167,
      168,
      169,
      170,
      171,
      172,
      173,
      174,
      175,
      176,
      177,
      178,
      179,
      180,
      181,
      182,
      183,
      184,
      185,
      186,
      187,
      188,
      189,
      190,
      191,
      192,
      193,
      194,
      195,
      196,
      197
    ],
    "train_loss": [
      0.43274566453579083,
      0.27830864530364446,
      0.24691647214154636,
      0.2299775896013823,
      0.2202882397615983,
      0.21166456020363114,
      0.20821959296362777,
      0.19976835330903317,
      0.19706848264122817,
      0.19228779686267955,
      0.18576682302594308,
      0.18067800019293825,
      0.17819950877358634,
      0.17572846623369826,
      0.1740446833347956,
      0.17086580145689326,
      0.16897618534925535,
      0.16605172117454325,
      0.1651113228963209,
      0.16407457336385842,
      0.16177985323674254,
      0.1607829834587333,
      0.16159958199331734,
      0.15959942504274288,
      0.1552697396476401,
      0.15558550138697372,
      0.1554746851057441,
      0.1550668668328737,
      0.1493148959087463,
      0.151393147570589,
      0.15055983146798801,
      0.15200283907243017,
      0.15017538120718782,
      0.1479992060465743,
      0.1473246998645331,
      0.14784777439794305,
      0.14778526817921983,
      0.14695151779454693,
      0.1473935899377756,
      0.14317386783946165,
      0.1429230266596153,
      0.14320419059388756,
      0.14043484658209282,
      0.1405340458188548,
      0.14391052542878396,
      0.14235396967247976,
      0.14176314802751472,
      0.14137510562448424,
      0.14027562953451464,
      0.13813335129971105,
      0.14101535094478548,
      0.13975391797377337,
      0.13846826534995427,
      0.14097445094628233,
      0.1386176983488025,
      0.1382635030025791,
      0.13616102788522802,
      0.1353087860473521,
      0.13534031083770076,
      0.1356632397278356,
      0.13688258191579242,
      0.132420880133224,
      0.1365105928016923,
      0.13700315959009987,
      0.13534175551923164,
      0.13511307866218428,
      0.134538003849893,
      0.133883531610092,
      0.13390177432419,
      0.1355863630727675,
      0.1290357447319639,
      0.13333156138559132,
      0.13192506765553957,
      0.1327990161942145,
      0.13353344614595067,
      0.1315069792170045,
      0.13393352200215508,
      0.13349604067331006,
      0.1323017220611585,
      0.13055059622271725,
      0.1288583710896718,
      0.1313353662793379,
      0.13116682201562752,
      0.13119017477197456,
      0.13066093437373638,
      0.12887772245704363,
      0.1327313949808425,
      0.12994122727482119,
      0.13344629775692615,
      0.13364984545419006,
      0.12792914537086952,
      0.1283496720539554,
      0.12884176555369192,
      0.13124043084088505,
      0.12991229147235053,
      0.12972100849443519,
      0.13039061320078807,
      0.1304517089833184,
      0.1284842519218598,
      0.12822898233327545,
      0.1280315305861817,
      0.12978457870977758,
      0.128302415472581,
      0.1274923721768952,
      0.128906980456986,
      0.12810242179114126,
      0.1285756191400273,
      0.12880961150370573,
      0.13071851670673226,
      0.12847390873458,
      0.12812527404642216,
      0.12608714757430792,
      0.1260756371335426,
      0.128010306115515,
      0.12686729614263073,
      0.1261836607573031,
      0.1282165418123361,
      0.12809694530762514,
      0.12763307980806965,
      0.12922931833239534,
      0.12779070874183926,
      0.12718984340362943,
      0.12492623656754955,
      0.12735780399233454,
      0.12686584715188132,
      0.1274573695174528,
      0.1266518918106408,
      0.12665844785518804,
      0.12648851089580906,
      0.12708515815796181,
      0.12566142597485652,
      0.12257932808026557,
      0.12476898759236514,
      0.12691659023703336,
      0.1258504048817475,
      0.12465888194514275,
      0.12611288096031328,
      0.12395365726204638,
      0.12529829929866138,
      0.1237983382997481,
      0.12501302422174831,
      0.12419833518610575,
      0.1280371456212527,
      0.12254371517660405,
      0.1234689084578854,
      0.1234016535500721,
      0.12458514071630171,
      0.12291331261323775,
      0.12547951177615058,
      0.1250183101382208,
      0.12491110643575502,
      0.12568996192408624,
      0.1257575374056493,
      0.12428656689203385,
      0.12365702012426703,
      0.12215381079645356,
      0.1246279244434916,
      0.12234006496409137,
      0.12418179343114791,
      0.12662958212124195,
      0.12366767380656096,
      0.12361534073922101,
      0.12410419503405591,
      0.1240444400989517,
      0.1245531049877665,
      0.12256360599621098,
      0.1226531756509491,
      0.12363051138856491,
      0.12444551770177298,
      0.12176248948235521,
      0.12167953077002236,
      0.1211329981963747,
      0.12477754639999691,
      0.122134190502879,
      0.12309313743920465,
      0.12182549256095525,
      0.12327129798074023,
      0.12295838151740655,
      0.12258365160172538,
      0.1232487830668382,
      0.1219902086980056,
      0.12304764750746655,
      0.12267952918023896,
      0.12323723431712942,
      0.12299524300113863,
      0.12297918865903486,
      0.12386983994293238,
      0.1223437153471929,
      0.12257662523115458,
      0.12066670301145258,
      0.12132586561346005,
      0.12346543930662082,
      0.12189607646387011,
      0.12342744611639467,
      0.12263752608581528,
      0.1213198797724732,
      0.1214269354792284
    ],
    "val_loss": [
      0.40674624949425997,
      0.39590526481053073,
      0.43309435118547457,
      0.4450215790353849,
      0.4520027179828661,
      0.4963309418298527,
      0.5240835931219027,
      0.5228194951118823,
      0.6037428357465539,
      0.5879328453076814,
      0.5142849444093819,
      0.5837669661212824,
      0.5889597713055011,
      0.5698938041657745,
      0.5446099554439505,
      0.5621222019195556,
      0.5554206338337438,
      0.5511505684095942,
      0.6361016926294315,
      0.5465099144838528,
      0.5571144385698312,
      0.5320629142537089,
      0.579549886089956,
      0.5594072223512713,
      0.5453848884045007,
      0.505603388005388,
      0.5880187957586642,
      0.5252900089778586,
      0.5532296813979835,
      0.49845373788458147,
      0.4864367277947015,
      0.6139402870423423,
      0.5748374928078965,
      0.5243747319423867,
      0.49795185016122406,
      0.5173496491002465,
      0.4822682265571491,
      0.5202612782934468,
      0.5472518823817818,
      0.5442586496561587,
      0.5117652309065808,
      0.4934845726647063,
      0.5537079989419369,
      0.5296290944347125,
      0.5093883365749599,
      0.5815854373493952,
      0.5172038124082331,
      0.49768481916653184,
      0.5106254192437241,
      0.5574048948502113,
      0.5475623555615277,
      0.4667594531428314,
      0.46758885890423896,
      0.5103152816524049,
      0.5312095135896505,
      0.49566371077281274,
      0.5121988943950858,
      0.5145020639512711,
      0.5041775763124049,
      0.5423722095475225,
      0.5576854717633325,
      0.5105327679279321,
      0.47277465879381775,
      0.52511784401304,
      0.503569539578375,
      0.5351865137587051,
      0.49387779778795327,
      0.5004473417105075,
      0.4783590777280802,
      0.5763076230080542,
      0.5336962200835079,
      0.48500610846066905,
      0.4800729901133897,
      0.5052937694563123,
      0.5095760362724701,
      0.5271701344919062,
      0.5231643758758814,
      0.49682179114775743,
      0.46533836111158666,
      0.5465671767151641,
      0.5739454041876478,
      0.4881475382311615,
      0.5185314953639478,
      0.47720548305325877,
      0.4976125220071056,
      0.4908033474387523,
      0.5137185509957953,
      0.5416835351306164,
      0.4818458083503974,
      0.5293147793073141,
      0.49646856079915325,
      0.48011003933445423,
      0.5186936810657293,
      0.4706903414990374,
      0.5240845520071641,
      0.5219378412795995,
      0.5109481571677202,
      0.4910742803069646,
      0.4591382688301766,
      0.49619072715857787,
      0.5543666535865761,
      0.5190907041023591,
      0.5345683847001926,
      0.5465461316981358,
      0.4988844421363162,
      0.4815485258302289,
      0.4719046067781077,
      0.5190761278266321,
      0.5220748486365386,
      0.4621117851245189,
      0.47928152230685345,
      0.5433400000729961,
      0.5094794857733977,
      0.4726306581568575,
      0.5545298268650464,
      0.5333426933044088,
      0.5472360162187122,
      0.5095812847737423,
      0.4911897144140954,
      0.49464232751173887,
      0.4791160125040009,
      0.5078805366274483,
      0.4966047112010196,
      0.5067376466122216,
      0.4993288930037064,
      0.5295108500310404,
      0.49719342109328973,
      0.5715121813073843,
      0.508721412004468,
      0.5462818246401713,
      0.5230102759903063,
      0.46718165451538063,
      0.5052926254932751,
      0.5460637683773826,
      0.4889051231081614,
      0.49755782841029994,
      0.4896350303274429,
      0.5160342925144527,
      0.4914748627893225,
      0.4676864216962974,
      0.5329820598090838,
      0.4845443089743574,
      0.5190916282108087,
      0.4982746667669205,
      0.5313639354116902,
      0.4930860183285382,
      0.44953945255029704,
      0.4776109066730488,
      0.4603898501592482,
      0.4875179606729639,
      0.49389570334000504,
      0.5052796926773236,
      0.49219449739791676,
      0.46263174237962257,
      0.5837771168369019,
      0.470718758075894,
      0.5257864023664754,
      0.5280542046723965,
      0.4576600374397403,
      0.4668872076683416,
      0.5090180530519542,
      0.4561987358652903,
      0.5080650112541493,
      0.4877324100650713,
      0.5056244530720625,
      0.5330724163549746,
      0.53146136319209,
      0.47001198031409774,
      0.49109464716500867,
      0.49971855439825685,
      0.459749110096586,
      0.5172336247375983,
      0.5192307113798079,
      0.5197819570715199,
      0.4873581637790103,
      0.5280660776321046,
      0.4815640391882308,
      0.48328066681048826,
      0.490753209613219,
      0.5046050839706095,
      0.5696931186371934,
      0.48028344649397686,
      0.5011972253104884,
      0.48910689800531565,
      0.5403042716314336,
      0.4927342922209266,
      0.4610466345921605,
      0.45147557083271933,
      0.48520316864826724,
      0.4794417368750015,
      0.5089065301917984,
      0.4778080462829439,
      0.5224378324598966,
      0.5307898366790331,
      0.5402907974705725,
      0.49367111125392116,
      0.4787591502471955
    ],
    "best_epoch": 147,
    "best_val_loss": 0.44953945255029704,
    "best_val_abs_mse": 0.5800024271011353,
    "test_loss": 0.5237933016832222,
    "test_abs_mse": 1.2559906244277954,
    "tracker": {
      "initial_train_loss": 0.43274566453579083,
      "train_threshold": 0.1442485548452636,
      "best_tracking": true,
      "patience_active": true,
      "patience_best_train": null,
      "patience_best_val": 0.44953945255029704,
      "patience_no_improve_epochs": 50,
      "best_train_loss": Infinity,
      "forced_stop_due_to_threshold": false
    }
  },
  "model_files": {
    "best": "scripts/outputs/mlp-other-rate/trial_48_4e4859/best_model.pt",
    "last": "scripts/outputs/mlp-other-rate/trial_48_4e4859/last_model.pt"
  },
  "config_path": "/home/amoris/data-analysis-on-dbps/scripts/outputs/mlp-other-rate/trial_48_4e4859/config.yaml"
}